main.py
zk_synk-0.0.1.dist-info/METADATA
zk_synk-0.0.1.dist-info/WHEEL
zk_synk-0.0.1.dist-info/top_level.txt
zk_synk-0.0.1.dist-info/RECORD
